client_report/__ini__.py
client_report/cli.py
client_report/report.py
client_report12-0.1.4.dist-info/METADATA
client_report12-0.1.4.dist-info/WHEEL
client_report12-0.1.4.dist-info/entry_points.txt
client_report12-0.1.4.dist-info/top_level.txt
client_report12-0.1.4.dist-info/RECORD
